extended/typing.py
extended_typing-0.0.1.dist-info/LICENSE
extended_typing-0.0.1.dist-info/METADATA
extended_typing-0.0.1.dist-info/WHEEL
extended_typing-0.0.1.dist-info/top_level.txt
extended_typing-0.0.1.dist-info/RECORD
